<legacy_variants>
  <!-- classic -->
  <variant old="540x304" new="wide"/>
  <variant old="940x400" new="cinema"/>
  <variant old="148x84" new="wide"/>
  <variant old="220x124" new="wide"/>
  <variant old="368x220" new="wide"/>
  <variant old="368x110" new="panorama"/>
  <variant old="180x101" new="wide"/>
  <variant old="180xVar" new="default"/>
  <variant old="580x148" new="panorama"/>

  <!-- zon -->
  <variant old="zon-fullwidth" new="cinema"/>
  <variant old="zon-large" new="wide"/>
  <variant old="zon-thumbnail" new="wide"/>
  <variant old="zon-article-large" new="wide"/>
  <variant old="zon-topic" new="cinema"/>
  <variant old="zon-square" new="square"/>

  <!-- zmo -->
  <variant old="zmo-large" new="super"/>
  <variant old="zmo-medium" new="cinema"/>
  <variant old="zmo-small" new="cinema"/>
  <variant old="zmo-x-small" new="cinema"/>
  <variant old="zmo-landscape-large" new="wide"/>
  <variant old="zmo-landscape-small" new="wide"/>
  <variant old="zmo-square-small" new="square"/>
  <variant old="zmo-square-large" new="square"/>
  <variant old="zmo-upright" new="portrait"/>
  <variant old="zmo-lead-upright" new="portrait"/>
  <variant old="zmo-nextread" new="wide"/>
  <variant old="zmo-article-dream" new="tile"/>
  <variant old="zmo-card-picture" new="narrow"/>
  <variant old="zmo-print-cover" new="portrait"/>

  <!-- internal -->
  <variant old="og-image" new="wide"/>
  <variant old="twitter-image-small" new="square"/>
  <variant old="twitter-image-large" new="wide"/>

  <variant old="zmo-large-center" new="wide"/>
  <variant old="zmo-large-left" new="wide"/>
  <variant old="zmo-large-right" new="wide"/>
  <variant old="zmo-medium-center" new="wide"/>
  <variant old="zmo-medium-left" new="wide"/>
  <variant old="zmo-medium-right" new="wide"/>
  <variant old="zmo-small-center" new="wide"/>
  <variant old="zmo-small-left" new="portrait"/>
  <variant old="zmo-small-right" new="portrait"/>

  <variant old="zmo-xl" new="super"/>
  <variant old="zmo-xl-header" new="super"/>
  <variant old="zon-printbox" new="standard"/>
  <variant old="zon-printbox-x-cinema" new="cinema"/>
  <variant old="zon-column" new="portrait"/>

  <variant old="large" new="super"/>
  <variant old="small" new="super"/>
  <variant old="upright" new="narrow"/>

  <variant old="newsletter-540x304" new="wide"/>
  <variant old="newsletter-220x124" new="wide"/>
  <variant old="brightcove-still" new="wide"/>
  <variant old="brightcove-thumbnail" new="wide"/>
  <variant old="spektrum" new="wide"/>
</legacy_variants>
